IM/__init__.py
IM/im_calculation.py
IM/im_reader.py
IM/ims.py
IM/ko_matrices.py
IM/snr_calculation.py
IM/waveform_reading.py
IM/scripts/calculate_ims.py
IM/scripts/gen_ko_matrix.py
im_calculation-2025.12.3.dist-info/METADATA
im_calculation-2025.12.3.dist-info/WHEEL
im_calculation-2025.12.3.dist-info/entry_points.txt
im_calculation-2025.12.3.dist-info/top_level.txt
im_calculation-2025.12.3.dist-info/RECORD
