Metadata-Version: 2.4
Name: im-calculation
Version: 2025.12.3
Summary: Intensity Measure Calculation for Ground Motion Waveforms
Author: ucgmsim
Requires-Python: >=3.11
Requires-Dist: numba
Requires-Dist: numpy
Requires-Dist: numexpr
Requires-Dist: pandas[hdf5]
Requires-Dist: pyfftw
Requires-Dist: scipy
Requires-Dist: pint-xarray
Requires-Dist: xarray[io]
Requires-Dist: typer>0.12.3
Requires-Dist: qcore-utils>=2025.12.1
Provides-Extra: ko-matrix
Requires-Dist: obspy; extra == "ko-matrix"
Provides-Extra: test
Requires-Dist: pytest; extra == "test"
Requires-Dist: hypothesis[numpy]; extra == "test"
Requires-Dist: obspy; extra == "test"
Requires-Dist: pytest-cov; extra == "test"
Provides-Extra: types
Requires-Dist: pandas-stubs; extra == "types"
Requires-Dist: scipy-stubs; extra == "types"
Provides-Extra: dev
Requires-Dist: deptry; extra == "dev"
Requires-Dist: ruff; extra == "dev"
Requires-Dist: ty; extra == "dev"
